assets/pages.txt
grabber/__init__.py
grabber/__main__.py
grabber/controllers/__init__.py
grabber/controllers/base.py
grabber/core/__init__.py
grabber/core/bot/__init__.py
grabber/core/bot/core.py
grabber/core/exc.py
grabber/core/settings.py
grabber/core/sources/__init__.py
grabber/core/sources/buondua.py
grabber/core/sources/bypass.py
grabber/core/sources/common.py
grabber/core/sources/everia.py
grabber/core/sources/graph.py
grabber/core/sources/hotgirl_asia.py
grabber/core/sources/khd.py
grabber/core/sources/kup.py
grabber/core/sources/nudecosplay.py
grabber/core/sources/xasiat.py
grabber/core/sources/xiuren.py
grabber/core/sources/yellow.py
grabber/core/utils.py
grabber/core/version.py
grabber/templates/__init__.py
grabberlib-0.1.12.dist-info/METADATA
grabberlib-0.1.12.dist-info/WHEEL
grabberlib-0.1.12.dist-info/entry_points.txt
grabberlib-0.1.12.dist-info/RECORD
