Metadata-Version: 2.1
Name: grabberlib
Version: 0.1.12
Summary: 
Author: grabber
Requires-Python: >=3.10,<4.0
Classifier: Programming Language :: Python :: 3
Classifier: Programming Language :: Python :: 3.10
Classifier: Programming Language :: Python :: 3.11
Classifier: Programming Language :: Python :: 3.12
Requires-Dist: aiogram (>=3.4.1,<4.0.0)
Requires-Dist: alive-progress (>=3.1.5,<4.0.0)
Requires-Dist: beautifulsoup4 (>=4.12.3,<5.0.0)
Requires-Dist: casefy (>=0.1.7,<0.2.0)
Requires-Dist: cement (>=3.0.8,<4.0.0)
Requires-Dist: colorama (>=0.4.6,<0.5.0)
Requires-Dist: colorlog (>=6.8.2,<7.0.0)
Requires-Dist: defusedxml (>=0.7.1,<0.8.0)
Requires-Dist: environs (>=8.0.0,<9.0.0)
Requires-Dist: httpx (>=0.23.3,<0.24.0)
Requires-Dist: jinja2 (>=3.1.3,<4.0.0)
Requires-Dist: lxml (>=5.2.1,<6.0.0)
Requires-Dist: olefile (>=0.47,<0.48)
Requires-Dist: patool (>=2.1.1,<3.0.0)
Requires-Dist: pillow (>=10.3.0,<11.0.0)
Requires-Dist: psycopg[binary,pool] (>=3.1.13,<4.0.0)
Requires-Dist: pybypass (>=2.0.1,<3.0.0)
Requires-Dist: python-twitter (>=3.5,<4.0)
Requires-Dist: requests (>=2.31.0,<3.0.0)
Requires-Dist: requests-html (>=0.10.0,<0.11.0)
Requires-Dist: rich (>=13.7.1,<14.0.0)
Requires-Dist: streamlit (>=1.35.0,<2.0.0)
Requires-Dist: streamlit-extras (>=0.4.3,<0.5.0)
Requires-Dist: telegraph (>=2.2.0,<3.0.0)
Requires-Dist: tenacity (>=8.2.3,<9.0.0)
Requires-Dist: tqdm (>=4.66.4,<5.0.0)
Requires-Dist: unipath (>=1.1,<2.0)
